sanan/__init__.py
sanan/hello.py
sanan-0.1.0.dist-info/METADATA
sanan-0.1.0.dist-info/WHEEL
sanan-0.1.0.dist-info/entry_points.txt
sanan-0.1.0.dist-info/RECORD
